{
  "chiplets": [
    {
      "name": "B",
      "x-position": 8.75,
      "y-position": 12.687027298046694,
      "width": 8.25,
      "height": 9.0,
      "rotation": 0,
      "power": 150
    },
    {
      "name": "F",
      "x-position": 0.0,
      "y-position": 12.49496062367664,
      "width": 8.75,
      "height": 8.75,
      "rotation": 0,
      "power": 20
    },
    {
      "name": "H",
      "x-position": 33.5,
      "y-position": 12.254817949381838,
      "width": 8.75,
      "height": 8.75,
      "rotation": 0,
      "power": 20
    },
    {
      "name": "G",
      "x-position": 25.25,
      "y-position": 21.004817949381838,
      "width": 8.75,
      "height": 8.75,
      "rotation": 0,
      "power": 20
    },
    {
      "name": "D",
      "x-position": 25.25,
      "y-position": 11.233831659747025,
      "width": 8.25,
      "height": 9.0,
      "rotation": 0,
      "power": 150
    },
    {
      "name": "C",
      "x-position": 17.0,
      "y-position": 15.96226349275404,
      "width": 8.25,
      "height": 9.0,
      "rotation": 0,
      "power": 150
    },
    {
      "name": "A",
      "x-position": 17.0,
      "y-position": 4.687027298046694,
      "width": 8.25,
      "height": 9.0,
      "rotation": 0,
      "power": 150
    },
    {
      "name": "E",
      "x-position": 25.25,
      "y-position": 0.0,
      "width": 8.75,
      "height": 8.75,
      "rotation": 0,
      "power": 20
    }
  ],
  "connections": [
    {
      "node1": "A",
      "node2": "B",
      "EMIBType": "interfaceB",
      "EMIB_length": 0.8533,
      "EMIB_max_width": 5,
      "EMIB_width": 2.0,
      "EMIB_bump_width": 1.0,
      "EMIB-x-position": 16.0,
      "EMIB-y-position": 12.760377298046693,
      "EMIB-rotation": 1
    },
    {
      "node1": "A",
      "node2": "D",
      "EMIBType": "interfaceB",
      "EMIB_length": 0.8533,
      "EMIB_max_width": 5,
      "EMIB_width": 2.0,
      "EMIB_bump_width": 1.0,
      "EMIB-x-position": 24.25,
      "EMIB-y-position": 12.033779478896859,
      "EMIB-rotation": 1
    },
    {
      "node1": "A",
      "node2": "E",
      "EMIBType": "interfaceB",
      "EMIB_length": 0.8533,
      "EMIB_max_width": 5,
      "EMIB_width": 2.0,
      "EMIB_bump_width": 1.0,
      "EMIB-x-position": 24.25,
      "EMIB-y-position": 6.291863649023346,
      "EMIB-rotation": 1
    },
    {
      "node1": "B",
      "node2": "C",
      "EMIBType": "interfaceB",
      "EMIB_length": 0.8533,
      "EMIB_max_width": 5,
      "EMIB_width": 2.0,
      "EMIB_bump_width": 1.0,
      "EMIB-x-position": 16.0,
      "EMIB-y-position": 18.39799539540037,
      "EMIB-rotation": 1
    },
    {
      "node1": "B",
      "node2": "F",
      "EMIBType": "interfaceB",
      "EMIB_length": 0.8533,
      "EMIB_max_width": 5,
      "EMIB_width": 2.0,
      "EMIB_bump_width": 1.0,
      "EMIB-x-position": 7.75,
      "EMIB-y-position": 16.539343960861668,
      "EMIB-rotation": 1
    },
    {
      "node1": "C",
      "node2": "D",
      "EMIBType": "interfaceB",
      "EMIB_length": 0.8533,
      "EMIB_max_width": 5,
      "EMIB_width": 2.0,
      "EMIB_bump_width": 1.0,
      "EMIB-x-position": 24.25,
      "EMIB-y-position": 17.671397576250534,
      "EMIB-rotation": 1
    },
    {
      "node1": "C",
      "node2": "G",
      "EMIBType": "interfaceB",
      "EMIB_length": 0.8533,
      "EMIB_max_width": 5,
      "EMIB_width": 2.0,
      "EMIB_bump_width": 1.0,
      "EMIB-x-position": 24.25,
      "EMIB-y-position": 22.55689072106794,
      "EMIB-rotation": 1
    },
    {
      "node1": "D",
      "node2": "H",
      "EMIBType": "interfaceB",
      "EMIB_length": 0.8533,
      "EMIB_max_width": 5,
      "EMIB_width": 2.0,
      "EMIB_bump_width": 1.0,
      "EMIB-x-position": 32.5,
      "EMIB-y-position": 15.817674804564431,
      "EMIB-rotation": 1
    }
  ],
  "wirelength": 55449.34327864194,
  "area": 1257.1410583613826,
  "aspect_ratio": 1.42
}